ttsdg/__init__.py
ttsdg/ttsdg.py
ttsdg-1.1.3.data/scripts/__init__.py
ttsdg-1.1.3.dist-info/LICENSE
ttsdg-1.1.3.dist-info/METADATA
ttsdg-1.1.3.dist-info/WHEEL
ttsdg-1.1.3.dist-info/top_level.txt
ttsdg-1.1.3.dist-info/RECORD
