Metadata-Version: 2.1
Name: ttsdg
Version: 1.1.3
Summary: A package to automate TTS data generation
Home-page: https://github.com/CharlesAverill/ttsdg
Author: Charles Averill
Author-email: charlesaverill20@gmail.com
License: UNKNOWN
Platform: UNKNOWN
Classifier: Programming Language :: Python :: 3
Classifier: License :: OSI Approved :: MIT License
Classifier: Operating System :: OS Independent
Requires-Dist: pyttsx3
Requires-Dist: pydub
